dnn_cool_train_loop/__init__.py
dnn_cool_train_loop/metrics.py
dnn_cool_train_loop/task_loop.py
dnn_cool_train_loop/train_loop.py
dnn_cool_train_loop/valid_loop.py
dnn_cool_train_loop-0.2.1.dist-info/LICENSE
dnn_cool_train_loop-0.2.1.dist-info/METADATA
dnn_cool_train_loop-0.2.1.dist-info/WHEEL
dnn_cool_train_loop-0.2.1.dist-info/top_level.txt
dnn_cool_train_loop-0.2.1.dist-info/RECORD
